{"name":"hrdb","description":"Queries for hrdb","queries":[{"name":"noOfDepartments","query":"SELECT COUNT(NAME) FROM DEPARTMENT","comment":"","description":null,"nativeSql":true,"returnsSingleResult":false,"update":false,"queryParams":[],"outputType":"hrdbnoOfDepartmentsrtnType"},{"name":"TotalBudget","query":"select sum(budget) from department","comment":"","description":null,"nativeSql":true,"returnsSingleResult":false,"update":false,"queryParams":[],"outputType":"hrdbTotalBudgetrtnType"},{"name":"NoOfEmployee","query":"select count(eid) from employee","comment":"","description":null,"nativeSql":true,"returnsSingleResult":false,"update":false,"queryParams":[],"outputType":"hrdbNoOfEmployeertnType"},{"name":"EngineeringEmployees","query":"select * from EMPLOYEE where DEPTID=1","comment":"","description":null,"nativeSql":true,"returnsSingleResult":false,"update":false,"queryParams":[],"outputType":"hrdbEngineeringEmployeesrtnType"},{"name":"MarketingEmployees","query":"select * from EMPLOYEE where DEPTID=2","comment":"","description":null,"nativeSql":true,"returnsSingleResult":false,"update":false,"queryParams":[],"outputType":"hrdbMarketingEmployeesrtnType"},{"name":"ProfessionalServicesEmployees","query":"select * from EMPLOYEE where DEPTID=5","comment":"","description":null,"nativeSql":true,"returnsSingleResult":false,"update":false,"queryParams":[],"outputType":"hrdbProfessionalServicesEmployeesrtnType"},{"name":"GeneralAndAdminEmployees","query":"select * from EMPLOYEE where DEPTID=3","comment":"","description":null,"nativeSql":true,"returnsSingleResult":false,"update":false,"queryParams":[],"outputType":"hrdbGeneralAndAdminEmployeesrtnType"},{"name":"SalesEmployees","query":"select * from EMPLOYEE where DEPTID=4","comment":"","description":null,"nativeSql":true,"returnsSingleResult":false,"update":false,"queryParams":[],"outputType":null},{"name":"SelectedEmployeeID","query":"select * from employee where eid=:data","comment":"","description":null,"nativeSql":true,"returnsSingleResult":false,"update":false,"queryParams":[{"paramName":"data","paramType":"java.lang.Integer","list":false}],"outputType":null},{"name":"NoOfDepartment","query":"SELECT COUNT(NAME) FROM DEPARTMENT","comment":"","description":null,"nativeSql":true,"returnsSingleResult":false,"update":false,"queryParams":[],"outputType":null}]}